emoji_tools/__init__.py
emoji_tools/core.py
emoji_tools/unicode_codes/__init__.py
emoji_tools/unicode_codes/de.py
emoji_tools/unicode_codes/en.py
emoji_tools/unicode_codes/es.py
emoji_tools/unicode_codes/fr.py
emoji_tools/unicode_codes/it.py
emoji_tools/unicode_codes/pt.py
emoji_tools-0.0.1.dist-info/LICENSE
emoji_tools-0.0.1.dist-info/METADATA
emoji_tools-0.0.1.dist-info/WHEEL
emoji_tools-0.0.1.dist-info/top_level.txt
emoji_tools-0.0.1.dist-info/RECORD
